{
  "data": {
    "weblink": "https://www.speedrun.com/deltarune_category_extensions?h=chapter-4-mike-glitched&x=9kvvjm0k-yn262jel.q5vew6rl-6njp2z6n.139edx31",
    "game": "y6552z86",
    "category": "9kvvjm0k",
    "level": null,
    "platform": null,
    "region": null,
    "emulators": null,
    "video-only": false,
    "timing": "ingame",
    "values": {
      "yn262jel": "q5vew6rl",
      "6njp2z6n": "139edx31"
    },
    "runs": [
      {
        "place": 1,
        "run": {
          "id": "m7vwdxwm",
          "weblink": "https://www.speedrun.com/deltarune_category_extensions/runs/m7vwdxwm",
          "game": "y6552z86",
          "level": null,
          "category": "9kvvjm0k",
          "videos": {
            "links": [
              {
                "uri": "https://youtu.be/cp4-W_onsvk?si=H_dHGMZj5V-RK5FT"
              }
            ]
          },
          "comment": "Michael",
          "status": {
            "status": "verified",
            "examiner": "qj2ze5lj",
            "verify-date": "2025-11-23T07:28:14Z"
          },
          "players": [
            {
              "rel": "user",
              "id": "x3q542ej",
              "uri": "https://www.speedrun.com/api/v1/users/x3q542ej"
            }
          ],
          "date": "2025-11-22",
          "submitted": "2025-11-22T23:51:09Z",
          "times": {
            "primary": "PT9M17S",
            "primary_t": 557,
            "realtime": "PT9M17S",
            "realtime_t": 557,
            "realtime_noloads": null,
            "realtime_noloads_t": 0,
            "ingame": null,
            "ingame_t": 0
          },
          "system": {
            "platform": "7m6ylw9p",
            "emulated": false,
            "region": "o316x197"
          },
          "splits": null,
          "values": {
            "yn262jel": "q5vew6rl",
            "6njp2z6n": "139edx31",
            "j84p9228": "1w4ozkmq"
          }
        }
      },
      {
        "place": 2,
        "run": {
          "id": "z5w6qedz",
          "weblink": "https://www.speedrun.com/deltarune_category_extensions/runs/z5w6qedz",
          "game": "y6552z86",
          "level": null,
          "category": "9kvvjm0k",
          "videos": {
            "links": [
              {
                "uri": "https://youtu.be/pTZTH7UshFY"
              }
            ]
          },
          "comment": "shoutout to @willowsmots",
          "status": {
            "status": "verified",
            "examiner": "qj2ze5lj",
            "verify-date": "2025-08-21T07:50:40Z"
          },
          "players": [
            {
              "rel": "user",
              "id": "8eow646j",
              "uri": "https://www.speedrun.com/api/v1/users/8eow646j"
            }
          ],
          "date": "2025-08-21",
          "submitted": "2025-08-21T02:53:05Z",
          "times": {
            "primary": "PT9M18S",
            "primary_t": 558,
            "realtime": "PT9M18S",
            "realtime_t": 558,
            "realtime_noloads": null,
            "realtime_noloads_t": 0,
            "ingame": null,
            "ingame_t": 0
          },
          "system": {
            "platform": "7m6ylw9p",
            "emulated": false,
            "region": "o316x197"
          },
          "splits": null,
          "values": {
            "yn262jel": "q5vew6rl",
            "6njp2z6n": "139edx31",
            "j84p9228": "1w4ozkmq"
          }
        }
      },
      {
        "place": 3,
        "run": {
          "id": "me2wnx2m",
          "weblink": "https://www.speedrun.com/deltarune_category_extensions/runs/me2wnx2m",
          "game": "y6552z86",
          "level": null,
          "category": "9kvvjm0k",
          "videos": {
            "links": [
              {
                "uri": "https://youtu.be/ydxBewI56Cg"
              }
            ]
          },
          "comment": "Entering dark world to the start of the fight was kinda bad but still a really good time",
          "status": {
            "status": "verified",
            "examiner": "qj2ze5lj",
            "verify-date": "2025-07-27T09:16:55Z"
          },
          "players": [
            {
              "rel": "user",
              "id": "5j5w0qzj",
              "uri": "https://www.speedrun.com/api/v1/users/5j5w0qzj"
            }
          ],
          "date": "2025-07-26",
          "submitted": "2025-07-27T03:37:14Z",
          "times": {
            "primary": "PT9M21S",
            "primary_t": 561,
            "realtime": "PT9M21S",
            "realtime_t": 561,
            "realtime_noloads": null,
            "realtime_noloads_t": 0,
            "ingame": null,
            "ingame_t": 0
          },
          "system": {
            "platform": "8gej2n93",
            "emulated": false,
            "region": "o316x197"
          },
          "splits": null,
          "values": {
            "yn262jel": "q5vew6rl",
            "6njp2z6n": "139edx31",
            "j84p9228": "1w4ozkmq"
          }
        }
      },
      {
        "place": 4,
        "run": {
          "id": "zqp88e8m",
          "weblink": "https://www.speedrun.com/deltarune_category_extensions/runs/zqp88e8m",
          "game": "y6552z86",
          "level": null,
          "category": "9kvvjm0k",
          "videos": {
            "links": [
              {
                "uri": "https://youtube.com/watch?v=9Hab0Gl0O2Q"
              }
            ]
          },
          "comment": "look at ts guy using the BORING x key\n",
          "status": {
            "status": "verified",
            "examiner": "1xymkgzx",
            "verify-date": "2025-07-27T12:35:11Z"
          },
          "players": [
            {
              "rel": "user",
              "id": "qj2ze5lj",
              "uri": "https://www.speedrun.com/api/v1/users/qj2ze5lj"
            }
          ],
          "date": "2025-07-26",
          "submitted": "2025-07-26T18:52:59Z",
          "times": {
            "primary": "PT9M28S",
            "primary_t": 568,
            "realtime": "PT9M28S",
            "realtime_t": 568,
            "realtime_noloads": null,
            "realtime_noloads_t": 0,
            "ingame": null,
            "ingame_t": 0
          },
          "system": {
            "platform": "8gej2n93",
            "emulated": false,
            "region": "o316x197"
          },
          "splits": null,
          "values": {
            "yn262jel": "q5vew6rl",
            "6njp2z6n": "139edx31",
            "j84p9228": "1w4ozkmq"
          }
        }
      },
      {
        "place": 5,
        "run": {
          "id": "z00dq6jz",
          "weblink": "https://www.speedrun.com/deltarune_category_extensions/runs/z00dq6jz",
          "game": "y6552z86",
          "level": null,
          "category": "9kvvjm0k",
          "videos": {
            "links": [
              {
                "uri": "https://youtu.be/cXUviI1R-JA"
              }
            ]
          },
          "comment": "MIAOU",
          "status": {
            "status": "verified",
            "examiner": "qj2ze5lj",
            "verify-date": "2025-07-27T08:54:50Z"
          },
          "players": [
            {
              "rel": "user",
              "id": "o86e3ywx",
              "uri": "https://www.speedrun.com/api/v1/users/o86e3ywx"
            }
          ],
          "date": "2025-07-26",
          "submitted": "2025-07-26T22:42:29Z",
          "times": {
            "primary": "PT9M32S",
            "primary_t": 572,
            "realtime": "PT9M32S",
            "realtime_t": 572,
            "realtime_noloads": null,
            "realtime_noloads_t": 0,
            "ingame": null,
            "ingame_t": 0
          },
          "system": {
            "platform": "8gej2n93",
            "emulated": false,
            "region": "o316x197"
          },
          "splits": null,
          "values": {
            "yn262jel": "q5vew6rl",
            "6njp2z6n": "139edx31",
            "j84p9228": "1w4ozkmq"
          }
        }
      },
      {
        "place": 6,
        "run": {
          "id": "y68p186z",
          "weblink": "https://www.speedrun.com/deltarune_category_extensions/runs/y68p186z",
          "game": "y6552z86",
          "level": null,
          "category": "9kvvjm0k",
          "videos": {
            "links": [
              {
                "uri": "https://youtu.be/fNUY0yPSeGM"
              }
            ]
          },
          "comment": "glorp",
          "status": {
            "status": "verified",
            "examiner": "qj2ze5lj",
            "verify-date": "2025-10-11T07:55:31Z"
          },
          "players": [
            {
              "rel": "user",
              "id": "8ek6zn78",
              "uri": "https://www.speedrun.com/api/v1/users/8ek6zn78"
            }
          ],
          "date": "2025-10-11",
          "submitted": "2025-10-11T01:21:56Z",
          "times": {
            "primary": "PT9M43S",
            "primary_t": 583,
            "realtime": "PT9M43S",
            "realtime_t": 583,
            "realtime_noloads": null,
            "realtime_noloads_t": 0,
            "ingame": null,
            "ingame_t": 0
          },
          "system": {
            "platform": "8gej2n93",
            "emulated": false,
            "region": "o316x197"
          },
          "splits": null,
          "values": {
            "yn262jel": "q5vew6rl",
            "6njp2z6n": "139edx31",
            "j84p9228": "lmo6v981"
          }
        }
      },
      {
        "place": 7,
        "run": {
          "id": "y8gwwjnz",
          "weblink": "https://www.speedrun.com/deltarune_category_extensions/runs/y8gwwjnz",
          "game": "y6552z86",
          "level": null,
          "category": "9kvvjm0k",
          "videos": {
            "links": [
              {
                "uri": "https://youtu.be/udR0uf1y4jU"
              }
            ]
          },
          "comment": "mike",
          "status": {
            "status": "verified",
            "examiner": "qj2ze5lj",
            "verify-date": "2025-07-26T18:48:04Z"
          },
          "players": [
            {
              "rel": "user",
              "id": "8dg437l8",
              "uri": "https://www.speedrun.com/api/v1/users/8dg437l8"
            }
          ],
          "date": "2025-07-26",
          "submitted": "2025-07-26T18:19:16Z",
          "times": {
            "primary": "PT9M47S",
            "primary_t": 587,
            "realtime": "PT9M47S",
            "realtime_t": 587,
            "realtime_noloads": null,
            "realtime_noloads_t": 0,
            "ingame": null,
            "ingame_t": 0
          },
          "system": {
            "platform": "8gej2n93",
            "emulated": false,
            "region": "o316x197"
          },
          "splits": null,
          "values": {
            "yn262jel": "q5vew6rl",
            "6njp2z6n": "139edx31",
            "j84p9228": "1w4ozkmq"
          }
        }
      },
      {
        "place": 8,
        "run": {
          "id": "m7lno3wy",
          "weblink": "https://www.speedrun.com/deltarune_category_extensions/runs/m7lno3wy",
          "game": "y6552z86",
          "level": null,
          "category": "9kvvjm0k",
          "videos": {
            "links": [
              {
                "uri": "https://youtu.be/Csc2YmsaOJw"
              }
            ]
          },
          "comment": "I think I'm supposed to mark this as on emulator (Wine) but it doesn't let me",
          "status": {
            "status": "verified",
            "examiner": "qj2ze5lj",
            "verify-date": "2025-07-27T15:43:48Z"
          },
          "players": [
            {
              "rel": "user",
              "id": "xz71o0ej",
              "uri": "https://www.speedrun.com/api/v1/users/xz71o0ej"
            }
          ],
          "date": "2025-06-24",
          "submitted": "2025-07-27T00:21:31Z",
          "times": {
            "primary": "PT10M4S",
            "primary_t": 604,
            "realtime": "PT10M4S",
            "realtime_t": 604,
            "realtime_noloads": null,
            "realtime_noloads_t": 0,
            "ingame": null,
            "ingame_t": 0
          },
          "system": {
            "platform": "8gej2n93",
            "emulated": true,
            "region": "o316x197"
          },
          "splits": null,
          "values": {
            "yn262jel": "q5vew6rl",
            "6njp2z6n": "139edx31",
            "j84p9228": "1w4ozkmq"
          }
        }
      }
    ],
    "links": [
      {
        "rel": "game",
        "uri": "https://www.speedrun.com/api/v1/games/y6552z86"
      },
      {
        "rel": "category",
        "uri": "https://www.speedrun.com/api/v1/categories/9kvvjm0k"
      }
    ]
  }
}